uiflow/__init__.py
uiflow-0.0.0.dist-info/METADATA
uiflow-0.0.0.dist-info/WHEEL
uiflow-0.0.0.dist-info/top_level.txt
uiflow-0.0.0.dist-info/RECORD
